Metadata-Version: 1.0
Name: goel-dsnd
Version: 1.0
Summary: Gaussian and Binomial distributions
Home-page: UNKNOWN
Author: Test Test
Author-email: UNKNOWN
License: UNKNOWN
Platform: UNKNOWN
